cliprog/__init__.py
cliprog/progress.py
pycliprog_rj-1.0.0.dist-info/METADATA
pycliprog_rj-1.0.0.dist-info/WHEEL
pycliprog_rj-1.0.0.dist-info/RECORD
